omimgr/__init__.py
omimgr/__main__.py
omimgr/config.py
omimgr/configure.py
omimgr/gui.py
omimgr/om.py
omimgr/omimgr.py
omimgr/shared.py
omimgr/wrappers.py
omimgr/icons/omimgr.png
omimgr-0.3.0.dist-info/LICENSE
omimgr-0.3.0.dist-info/METADATA
omimgr-0.3.0.dist-info/WHEEL
omimgr-0.3.0.dist-info/entry_points.txt
omimgr-0.3.0.dist-info/top_level.txt
omimgr-0.3.0.dist-info/RECORD
