Metadata-Version: 2.1
Name: omimgr
Version: 0.3.0
Summary: Optical media imager
Home-page: https://github.com/KBNLresearch/omimgr
Author: Johan van der Knijff
Author-email: johan.vanderknijff@kb.nl
Maintainer: Johan van der Knijff
Maintainer-email: johan.vanderknijff@kb.nl
License: Apache License 2.0
Download-URL: https://github.com/KBNLresearch/omimgr/archive/0.3.0.tar.gz
Platform: linux
Classifier: Programming Language :: Python :: 3
Requires-Python: >=3.2
Requires-Dist: isolyzer
Requires-Dist: pytz
Requires-Dist: setuptools
Requires-Dist: tkfilebrowser
